{"timestamp": 1347044803500, "total": 12041, "urls": {"http://t.co/EhFTprll": 8, "http://t.co/doHjXBjH": 8, "http://t.co/PC1iy1oo": 11, "http://t.co/": 23, "http://t.c": 9, "http://t.co/CKUW2vbc": 29, "http://t.co/QCdT7Dvr": 12, "http://t.co/HeJlZrql": 6, "http://t.co/tIbfbEzo": 9, "http://t.co/AAsGBJkS": 16, "http://t.co/DENUrY2W": 8, "http://t.co/hhZXbka1": 25, "http://t.co/hIc2D1xK": 11, "http://t.co/rCU59qh7": 6, "http://t.co/XCRmZBCT": 8, "http://t.co/cr0tCb4N": 18, "http://t.co/AO8aVZop": 9, "http://t.co/xe6qtHoT": 25, "http://t.co/aOgcFl68": 65, "http://t.co/b3SbbFpM": 10, "http://t.co/WMAgplYE": 10, "http://t.co/xRyt76FX": 8, "http://t.co/IORZ2bCb": 11, "http://t.co/diboezZn": 9, "http://t.co/Onz9XHCH": 7, "http://t.co/qBlz6r80": 15, "http://t.co/WKMCoclj": 8, "http://t.co/1Fgzig7J": 12, "http://t.co/U3bcOwnA": 14, "http://t.co/SFKdQD94": 78, "http://t.co/kTpNmBvo": 331, "http://t.co/AVM9FxZ9": 107, "http://b": 9, "http://t.co": 7, "http://t.co/LrGrNaEM": 17, "http://t.co/vg5": 7, "http://t.": 45, "http://t": 14, "http://t.co/6BmDjZas": 11, "http://t.co/rZwxYq2a": 14}, "words": {"here.cm http": 836, "ceremony rehearsals": 852, "gold": 1279, "paralympic": 2101, "paralympic closing": 940, "a second": 762, "ceremony": 659, "rt coldplay": 1094, "sunset paralympics": 700, "great time": 866, "pic take": 688, "rehearsals": 546, "awesome performers": 848, "olympic gold": 574, "olympic park": 964, "coldplay": 663, "us proud": 854, "be here.cm": 842, "rehearsals having": 850, "http": 604, "time": 653, "share tonight's": 692, "paralympics": 4745, "so many": 878, "tonight's spectacular": 692, "london2012 pic": 700, "having great": 850, "the paralympics": 2814, "great": 721, "park sunset": 694, "gold medal": 542, "closing ceremony": 1226, "proud": 761, "awesome": 533, "paralympics http://t.co/ktpnmbvo": 662, "performers around": 848, "coldplay paralympic": 848, "many awesome": 848, "closing": 634, "to share": 694}, "tags": {"cbb": 69, "f1": 23, "teamusa": 21, "gold": 19, "paralympic": 272, "malaysia": 34, "london2012.": 36, "london": 55, "paralympicsgb": 23, "c4paralympics": 43, "teamgb": 278, "olympicstadium": 19, "wheelchairbasketball": 21, "teamashley": 30, "mbfw": 18, "amazing": 23, "sportrightnow": 22, "thankyougamesmakers": 53, "paralympics!": 20, "sittingvolleyball": 39, "goalball": 27, "paralympics.": 60, "3daystogo": 49, "ted,": 18, "fb": 22, "china": 17, "ff": 37, "news": 25, "paralympics2012": 34, "teamireland": 28, "cbbfinal": 35, "superhumans": 18, "proud": 22, "paralympi": 17, "celebbb": 108, "ourgreatestteam": 38, "paralympics": 2108, "athletics": 19, "tha": 41, "swimming": 53}}