{"timestamp": 1345048535500, "total": 14986, "urls": {"http://t.co/X4ts6hLr": 14, "http://t.co/rCJFSMRJ": 14, "http://t.co/cNOnd4eF": 11, "http://t.co/i3gVytwE": 10, "http://t.co/ilkXfM3Y": 42, "http://t.co/": 68, "http://t.co/af": 41, "http://t.co/pYIkOFx4": 18, "http://t.c": 127, "http://t.co/bjCd9ok0": 15, "http://t.co/pBrfa6EG": 44, "http://t.co/X": 10, "http://t.co/PLcxavdu": 10, "http://t.co/s6ldegMB": 41, "http://t.co/vS7FZWtO": 18, "http://t.co/ly1lMqz6": 15, "http://t.co/Uk": 21, "http://t.co/nm5bOTag": 19, "http://t.co/FS5Gowbk": 10, "http://t.co/83yqeLjj": 34, "http://t.co/GtQDYeWh": 24, "http://t.co/ob0FiR7s": 14, "http://t.co/3DIqvX24": 11, "http://t.co/Sq0jGXOc": 25, "http://t.co/YVPQVrd2": 26, "http://t.co/4Q0AwQlE": 82, "http://t.co/mRJ12E03": 25, "http://t.co/qrEKI76F": 14, "http://t.co/jsE2rZ6R": 72, "http://t.co/iq8ljI3k": 75, "http://t.co/DynHmx5f": 23, "http://t.co/L0kbaAQK": 18, "http://t.co/uMwLYEfp": 14, "http://t.co": 11, "http://t.co/7": 16, "http://t.co/gobtPZqT": 12, "http://t.": 45, "http://t": 21, "http://t.co/apjpcRXY": 13, "http://t.co/k2c29kSK": 14}, "words": {"mike rutherford": 570, "mason mike": 562, "the 2012": 816, "gold": 749, "olympic closing": 1176, "were here": 564, "one": 631, "some amazing": 572, "london": 1060, "rt edsheeran": 562, "1 album": 572, "with nick": 562, "niallofficial sandyymartinez": 572, "awards,number 1": 572, "ceremony": 1364, "the teen": 572, "the recording": 562, "amazing moments..winnin": 572, "performance": 604, "is 14": 560, "2012": 1214, "rt niallofficial": 1214, "moments..winnin brit": 572, "olympic games": 606, "london 2012": 784, "of wish": 562, "richard jones": 560, "teen choice": 572, "choice awards,number": 572, "and richard": 560, "olympics closing": 1552, "now": 546, "niallofficial": 649, "the paralympics": 634, "nick mason": 564, "closing ceremony": 2384, "team": 754, "14 o": 560, "closing": 1782, "olympic performance": 594}, "tags": {"poshspice": 99, "teamusa": 31, "england": 23, "apple": 99, "london2012:": 22, "win": 32, "manage": 19, "olympics,": 189, "london2012.": 23, "olympics.": 23, "london": 42, "corporatism": 19, "teamgb": 103, "paralympics?": 22, "nba2k13": 23, "usa": 24, "bigbrother": 99, "newiphone": 99, "1": 27, "paralympics!": 21, "mullingarshuffle": 33, "flocross": 21, "sneakers": 21, "london2012_official_mobile_game": 31, "closingceremony": 35, "business": 21, "1dpengantartidur": 81, "wheniwasyounger": 24, "news": 36, "flocountry": 19, "14": 281, "samsung": 100, "iphone5": 99, "rio": 22, "bringbacklondon2012": 23, "nasa": 99, "ourgreatestteam": 38, "paralympics": 45, "amnesty": 19, "dow": 25}}