{"timestamp": 1344238646000, "total": 38575, "urls": {"http://t.co/eHj2ehmt": 41, "http://t.co/CBubsksS": 53, "http://t.co/7olRaKzb": 99, "http://t.co/1IpZasJ9": 25, "http://t.co/": 87, "http://t.c": 74, "http://t.co/khPTAOIe": 181, "http://t.co/OKawgkRU\u201d": 24, "http://t.co/3o5lBMI5": 408, "http://t.co/seJbogwj": 28, "http://t.co/DkDNRNFY": 33, "http://t.co/rkTSSZ0j": 30, "http://t.co/5f": 22, "http://t.co/Biumfz0a": 16, "http://t.co/uE4AHROt": 29, "http://t.co/O1bdCfya": 33, "http://t.co/QJDE9xc3": 23, "http://t.co/z6LOcIK4": 23, "http://t.co/9GcmhXX2": 34, "http://t.co/E0lRH417": 21, "http://t.co/ShoTnfGh": 58, "https://t.co/5Jgog9Mz": 21, "http://t.co/rALOiqCD": 32, "http://t.co/zYzgSLRS": 19, "http://t.co/30tI5hZo": 26, "http://t.co/9rTIVQiG": 25, "http://t.co/NF8qHMYZ": 24, "http://t.co/ltbKWkf5": 54, "http://t.co/UB553C2C]": 30, "http://t.co/rpaB8HmA": 21, "http://t.co/yPWPIGdW": 19, "http://t.co/Zj5JDdYi": 74, "http://t.co/DsMiH6Qi": 102, "http://t.co/Dev7wxFL": 25, "http://t.co/E6DRsb2t": 37, "http://t.co": 46, "http://t.co/Tt6WZjBt": 38, "http://t.": 45, "http://t": 52, "http://t.co/kZB": 22}, "words": {"the 2012": 1090, "on mars": 1000, "gold": 2742, "over": 1278, "her name": 1068, "london": 2962, "100m": 1299, "the 400m": 1058, "amazing": 1549, "has anyone": 1086, "olympic gold": 1032, "olympic park": 2052, "usain": 1714, "today": 1442, "2012": 2551, "falls over": 1094, "good": 1554, "to watch": 1576, "watching": 1731, "park": 1120, "london 2012": 2144, "mars": 1109, "watch": 1484, "400m hurdles": 1190, "the london": 1132, "bolt": 1981, "an amazing": 1198, "medal": 1653, "day": 1242, "good morning": 1256, "olympic games": 1382, "usain bolt": 2652, "gold medal": 1208, "oh": 1001, "up": 1503, "morning": 1132, "games": 1204, "woman falls": 1062, "olympic stadium": 1730, "more": 1009}, "tags": {"teamusa": 78, "share_rt": 71, "olympics:": 65, "win": 57, "share": 72, "\u30aa\u30ea\u30f3\u30d4\u30c3\u30af": 62, "london2012.": 124, "olympics.": 93, "london": 148, "bbc": 54, "shooting": 253, "teamgb": 685, "inspiring": 237, "basketball": 108, "gold": 75, "fundnasa": 49, "tennis": 522, "diggretweetrt": 71, "marscuriosity:": 50, "yorkshire": 75, "msl": 52, "hockey": 66, "bbc2012": 293, "london2012festival": 56, "kaskus": 71, "london2012_official_mobile_game": 87, "unyu": 71, "rakyatkaskus": 71, "marscuriosity": 69, "bolt": 147, "curiosity": 97, "news": 86, "teamireland": 64, "diggretweet": 71, "volleyball": 69, "ourgreatestteam": 65, "athletics": 78, "olympics2012": 107, "usainbolt": 98, "getgluehd": 71}}