{"timestamp": 1345462701000, "total": 4563, "urls": {"http://t.co/E": 6, "http://t.co/luCmOnpe": 14, "http://t.co/jJVAE5d3": 7, "http://t.co/a4PuP8GY": 4, "http://t.co/y2wikLCg": 5, "http://t.co/": 25, "http://t.co/lNQVlVgv": 5, "http://t.co/kXmjkq41": 5, "http://t.c": 10, "http://t.co/d5mJcQgG\u2192": 5, "http://t.co/PLcxavdu": 5, "http://t.co/Fq61zuUK": 5, "http://t.co/ZT": 5, "http://t.co/aVGeRg8D": 7, "http://t.co/iCSQUqu3": 7, "http://t.co/CLjMM8Jx": 4, "http://t.co/P7fh6pGp": 6, "http://t.co/s": 7, "http://t.co/wMD23yl9": 7, "http://t.co/uKtAARXA": 5, "http://t.co/wuobudYV": 10, "http://t.co/alZCeDrW": 23, "http://t.co/Zp8LKaQ3": 5, "http://t.co/D6A6hMCl": 5, "http://t.co/sYas1uhO": 10, "http://t.co/0PHSaoDk": 17, "http://t.co/jUEPCIRf": 5, "http://t.co/Opv9JvUW": 4, "http://t.co/FCvKzQhw": 5, "http://t.co/vJAGDHaY": 5, "http://t.co/ETlLlEOu\u2192": 10, "http://t.co/uGi1ieSm": 6, "http://t.co/VbaZLn9p": 11, "http://t.co/JCEXcdMJ": 8, "http://t.co/DbVDFFdl": 10, "http://t.co": 33, "http://t.co/vFsxsiCY": 4, "http://t.co/8Bk6UU6X": 9, "http://t.": 14, "http://t": 26}, "words": {"via": 161, "gold": 245, "win": 180, "over": 97, "one": 177, "opening ceremony": 118, "see": 131, "legacy": 151, "london": 456, "tom daley": 124, "olympic sport": 110, "sport": 109, "out": 110, "ceremony": 206, "sports": 113, "olympian": 133, "olympic gold": 138, "new": 137, "to play": 122, "2012": 270, "olympic medal": 130, "good": 104, "london 2012": 264, "de": 116, "the london": 248, "post": 102, "now": 165, "medal": 218, "i'm": 94, "olympic games": 342, "great": 102, "in 2016": 96, "to see": 116, "gold medal": 128, "closing ceremony": 246, "up": 146, "games": 261, "team": 135, "closing": 150, "olympic legacy": 204}, "tags": {"qanda": 6, "beijing": 10, "xfactorau": 9, "naonlyfornaija": 14, "urldn": 5, "london2012:": 32, "win": 35, "paralympic": 10, "olympics,": 22, "fashion": 9, "design": 8, "nba": 13, "teamgb": 17, "win:": 18, "instantfollowback": 6, "qrgames": 6, "photography)": 7, "afc": 21, "oneword": 7, "closingceremony": 7, "wardust": 6, "gorin": 7, "excited": 16, "london2012_official_mobile_game": 47, "stagetaken": 8, "3\u00a0whose": 7, "realtalk": 6, "marketing": 6, "photography": 6, "ifwt": 13, "news": 17, "pbt": 6, "cadbury2012": 6, "newtag": 7, "volleyball": 7, "ourgreatestteam": 13, "paralympics": 18, "london": 53, "tokyo2020": 15, "rio2016": 6}}