{"timestamp": 1346191582000, "total": 5893, "urls": {"http://t.co/bguuH0uZ": 4, "http://t.co/Ieim7Dkp": 5, "http://t.co/": 7, "http://t.co/zZA9YgVc": 7, "http://t.co/u7iG9WH5": 6, "http://t.c": 5, "http://t.co/RqPTJa3k?": 4, "http://t.co/LU8SRupu": 4, "http://t.co/ypQpLoUp": 81, "http://t.co/syiNDT4e": 81, "http://t.co/4I": 4, "http://t.co/jgYs2zZ6": 10, "http://t.co/pPf8vvPQ": 4, "http://t.co/lmarbfsH": 34, "http://t.co/xe6qtHoT": 4, "http://t.co/krg2rhcz": 13, "http://t.co/b3elrV9q": 48, "http://t.co/uOVEwAbS": 3, "http://t.co/g5AaUvV5": 4, "http://t.co/6xcMgvrN": 9, "http://t.co/DPvAgnCh": 6, "http://t.co/iihk17ET": 3, "http://t.co/sPpfqNl1": 13, "http://t.co/f": 6, "http://t.co/3C5wnbA1": 6, "http://t.co/RDwdVdl9": 3, "http://t.co/zHdvjyWg": 12, "http://t.co/LnTo8um3": 6, "http://t.co/jbEGatpU": 7, "http://t.co/emjrVJxH": 6, "http://t.co/FZXyiZNZ": 4, "http://t.co/hq1reDCd": 16, "http://t.co/oif5CZXH": 11, "http://t.co/QQDz3SO0": 7, "http://t.co/LUBkOPba": 7, "http://t.": 69, "http://t.co/1OQxaJ7N": 4, "http://t.co/bkXpWaC6": 10, "http://t.co/6AkMfrFh": 6, "http://t.co/bmnUerrE": 4}, "words": {"paralympic games": 448, "rt c4paralympics": 274, "people": 273, "paralympic": 1062, "torch": 746, "to go": 194, "one": 351, "paralympic flame": 368, "the paralympic": 692, "see": 203, "london": 349, "torch relay": 278, "opening ceremony": 346, "tomorrow": 236, "ceremony": 231, "don't": 211, "start": 225, "flame": 197, "go": 192, "bbc news": 268, "over": 198, "today": 287, "2012": 372, "you ready": 228, "paralympics start": 336, "opening": 202, "london 2012": 280, "rt tomdaley1994": 250, "the torch": 254, "news": 216, "the paralympics": 1198, "almost over": 228, "olympic tattoo": 242, "games": 361, "paralympic torch": 430, "team": 195, "paralympics": 1453, "london2012 paralympics": 274, "start today": 252, "the waiting": 228}, "tags": {"voteonedirection": 83, "getjacklaugherto60k": 22, "goparalympicsgb": 40, "extraordinary2012": 38, "olympics:": 10, "paralympic": 131, "vinb": 42, "romney": 13, "bringiton": 12, "teamusa": 17, "london": 21, "paral\u00edmpicos": 12, "paratorch": 21, "sportrightnow": 19, "teamgb": 73, "10thingsimustdobeforeidie": 20, "usa": 13, "tomorrowspaperstoday": 16, "tomdaleyphotoaday": 130, "paralympics!": 13, "20hourstogo": 35, "paralympics.": 11, "gop": 43, "2012": 13, "torch": 14, "atos": 41, "mormon": 10, "obama2012": 77, "weed": 10, "vamosespa\u00f1a": 12, "torchrelay": 17, "news": 22, "ronan": 10, "brazilnocorrupt": 81, "socialshopper": 15, "openingceremony": 10, "socialolympics": 14, "ourgreatestteam": 44, "paralympics": 282, "olympics2012": 10}}