{"timestamp": 1344087446000, "total": 126528, "urls": {"http://t.co/6n6ccr1H": 82, "http://t.co/edZ4P9tF": 97, "http://t.co/ED0HGmC4": 225, "http://t.co/": 102, "http://t.co/JIYeBnvy": 49, "http://t.co/ugnKeM1u": 135, "http://t.c": 143, "http://t.co/gckV7iTs": 57, "http://t.co/RFEkXawP": 30, "http://t.co/A97UxSVl": 31, "http://t.co/8ZabMWBd": 142, "http://t.co/38ez8QCj": 112, "http://t.co/YNxgZ": 80, "http://t.co/Chl72ZHx": 83, "http://t.co/gn1FiGIR": 35, "http://t.co/rALOiqCD": 31, "http://t.co/4YNpdOCg": 42, "http://t.co/6B2pJUUY": 29, "http://t.co/tm8L8fAa\u201d": 33, "http://t.co/FYkgR7V1": 54, "http://t.co/AoOo": 37, "http://t.co/oJGqxFzD": 59, "http://t.co/ShoTnfGh": 637, "http://t.co/eYIJGrXK": 437, "http://t.co/XaoLpNMW": 56, "http://t.co/qGH": 53, "http://t.co/AIukAf7J": 38, "http://t.co/7RNzWgve": 28, "http://t.co/BEJOgmNG": 41, "http://t.co/7INYWojG": 234, "http://t.co/O8T4xnPD": 34, "http://t.co/UQpWZYiV": 77, "http://t.co/4YKmcdGy": 40, "http://t.co/rkMHO0k9": 94, "http://t.co": 307, "http://t.co/PitHSL87": 71, "http://t.": 104, "http://t": 56, "http://t.co/2xVmeyQv": 37, "http://t.co/45ZwfUaq": 86}, "words": {"everyone": 5787, "gold": 28587, "win": 6566, "soo hooked": 10072, "im": 5588, "serena williams": 25614, "like everyone": 10088, "im soo": 10074, "yo yo": 10152, "the last": 5190, "maria sharapova": 9816, "yo": 10430, "usa": 7636, "niallofficial yo": 10046, "tennis": 9272, "hooked": 5226, "sharapova": 8152, "olympic gold": 13224, "watching": 7088, "maria": 5717, "the gold": 9348, "williams": 13784, "rt niallofficial": 10032, "serena": 20643, "i suppose": 10002, "singles": 6435, "chillin im": 10072, "6-0 6-1": 5444, "on chillin": 10072, "whats goin": 10086, "i don't": 5932, "medal": 11406, "yo whats": 10074, "niallofficial": 6832, "to win": 7290, "gold medal": 16740, "wins": 5895, "serenawilliams": 5994, "london": 5535, "first": 6650}, "tags": {"teamusa": 2519, "booyah": 174, "gold": 925, "mexico": 253, "getgluehd!": 531, "\u30aa\u30ea\u30f3\u30d4\u30c3\u30af": 800, "senegal": 225, "olympics.": 393, "london": 318, "gocanada": 222, "teamgb": 1143, "canada": 483, "triathlon": 181, "basketball": 759, "usa": 1818, "lo": 1157, "tennis": 3832, "lithuania": 176, "sharapova": 227, "bbc2012": 423, "\u5353\u7403": 788, "jjoo": 142, "teamcanada": 346, "gocanadago": 308, "football": 173, "usabasketball": 174, "serena": 661, "trampoline": 589, "ctvolympics": 143, "fb": 168, "goldmedal": 228, "boxing": 183, "olympics,": 164, "london2012.": 224, "badminton": 269, "serenawilliams": 705, "lochte": 151, "\u30d0\u30c9\u30df\u30f3\u30c8\u30f3": 632, "olympics2012": 560, "getgluehd": 622}}