{"timestamp": 1344001046000, "total": 117532, "urls": {"http://t.co/fKNfO0Uy": 50, "http://t.co/fkCfnPxE": 42, "http://t.co/lz6": 78, "http://t.co/qG0bWp5T": 73, "http://t.co/82u5OCA9": 63, "http://t.c": 118, "http://t.co/": 351, "http://t.co/rO5keH0h": 73, "http://t.co/9oWawoyW": 71, "http://t.co/d": 278, "http://t.co/4VeiR4ff": 233, "http://t.co/Bpnxuoly": 39, "http://t.co/dt5d": 169, "http://t.co/ZiUB": 52, "http://t.co/rrDZhNH9": 31, "http://t.co/Ig4GpjRs": 67, "http://t.co/dlOHH8TP": 45, "http://t.co/LE9xSOnR": 44, "http://t.co/jAanax8z": 58, "http://t.co/Ds1zDFpv": 58, "http://t.co/ShoTnfGh": 787, "http://t.co/wzcDczL1": 77, "http://t.co/V0f5Lnq3": 79, "http://t.co/Tj9yUYE5": 32, "http://t.co/wcAqwpg9": 35, "http://t.co/TSg2hHvn": 101, "http://t.co/FmT4ueqt": 36, "http://t.co/YVuL8": 30, "http://t.co/BmX3OB7N": 45, "http://t.co/qkKXTGE7": 50, "http://t.co/WmvUiuTt": 45, "http://t.co/CwHfDY7P": 50, "http://t.co/kyE83D9C": 185, "http://t.co": 170, "http://t.co/Fo0g5ZXl": 111, "http://t.": 136, "http://t": 176, "http://t.co/XUIQSonO": 39, "http://t.co/8iN5Lm8E": 33, "http://t.co/9ATtVwYg": 773}, "words": {"love": 3415, "del potro": 5544, "gold": 6363, "regina george": 3518, "london": 5156, "dong": 4179, "go": 3030, "olympic sport": 3472, "sport": 3379, "event": 3284, "out": 3251, "usa": 3444, "men's": 3068, "tennis": 4571, "field": 3529, "federer": 4330, "final": 3419, "today": 3456, "2012": 4729, "good": 3576, "dong dong": 4060, "to watch": 3056, "watching": 8300, "track": 6024, "london 2012": 3142, "trampoline": 3397, "watch": 4304, "vijay kumar": 6252, "now": 3860, "medal": 5408, "silver": 3732, "kumar": 3238, "up": 3541, "amp field": 3234, "del": 3248, "team": 3781, "i'm": 4045, "vijay": 3563, "and field": 3182, "first": 3084}, "tags": {"teamusa": 806, "teamusa\u2019s": 288, "london2012:": 356, "towie": 564, "india": 319, "getgluehd!": 410, "\u30aa\u30ea\u30f3\u30d4\u30c3\u30af": 754, "jjoo": 209, "olympics.": 371, "uswnt": 403, "shooting": 237, "delpotro": 394, "teamgb": 1513, "gold": 190, "usa": 697, "olym": 331, "boxing": 184, "tennis": 1939, "vijaykumar": 165, "hockey": 326, "bbc2012": 268, "federer": 837, "archery": 199, "trampoline": 266, "nhk": 258, "ff": 381, "olympictennis": 357, "bronze": 476, "getstarted": 283, "judo": 1168, "dressage": 183, "\u30a2\u30fc\u30c1\u30a7\u30ea\u30fc": 413, "trackandfield": 289, "tracknation": 433, "london2012.": 182, "jeah-worthy": 286, "teamgb's": 437, "london": 299, "olympics2012": 460, "getgluehd": 561}}