{"timestamp": 1344958535000, "total": 24137, "urls": {"http://t.co/DLjVOjTZ": 18, "http://t.co/": 62, "http://t.co/rdULPpmg": 43, "http://t.c": 55, "https://t.co/aKl3NoXw": 24, "http://t.co/88AEupci": 38, "http://t.co/pBrfa6EG": 34, "http://t.co/K65VC17J": 98, "http://t.co/RRHNKBxE": 28, "http://t.co/gVEPRwMU": 34, "http://t.co/L8o2Lop5": 36, "http://t.co/17CL91PG": 181, "http://t.co/hBK": 25, "http://t.co/l": 16, "http://t.co/cehFQc8l": 16, "http://t.co/9zrLwV55": 133, "http://t.co/OmLEXLXP": 37, "http://t.co/ryyXJuzC": 36, "http://t.co/tlIvpeyz": 20, "http://t.co/oW9QZVAW": 16, "http://t.co/8KVOg9g2": 60, "http://t.co/wwV4xoNm": 25, "http://t.co/3iW5RYPB": 44, "http://t.co/NSUqVZRA": 39, "http://t.co/3KiA35Jq": 31, "http://t.co/Oo72QXa0": 18, "http://t.co/9jCYnADg": 25, "http://t.": 26, "http://t.co/YkCdiBal": 36, "http://t.co/jAaGikJP": 24, "http://t.co/mRJ12E03": 21, "http://t.co/E0S4uYZ7": 19, "http://t.co/ypCV3ZHt": 17, "http://t.co/sd90500A": 64, "http://t.co": 38, "http://t.co/qhLkbV67": 125, "http://t.co/n9NaMOLp": 83, "http://t": 36, "http://t.co/ZwpJG2YO": 56, "http://t.co/iq9ntbFm": 27}, "words": {"via": 1043, "gold": 1429, "olympic medal": 642, "over": 1148, "olympic closing": 652, "back": 799, "one": 1172, "london": 2317, "all enough": 670, "you guys": 778, "ceremony": 1519, "are over": 1284, "people": 605, "olympian": 678, "olympic gold": 844, "olympics closing": 822, "out": 621, "medals": 786, "2012": 1812, "olympics can't": 696, "london 2012": 1454, "the gig": 670, "the london": 1074, "new": 736, "world": 709, "now": 1011, "medal": 954, "i'm": 775, "olympic games": 1528, "olympic ceremony": 720, "can't thank": 672, "a country": 622, "closing ceremony": 1878, "one direction": 776, "games": 1149, "rt louis_tomlinson": 1056, "team": 805, "closing": 1165, "athletes": 671, "to perform": 1016}, "tags": {"20thingsidontlike:": 42, "teamusa": 38, "olympics:": 29, "win": 30, "groupon": 29, "i4tandt": 30, "london2012,": 62, "olympics,": 37, "london2012.": 53, "olympics.": 39, "london": 95, "spicegirls": 24, "teamgb": 97, "20thingsidontlike": 49, "usa": 37, "socialmedia": 24, "1": 30, "olympian": 23, "closingceremony": 94, "new": 62, "cadbury2012": 50, "london2012_official_mobile_game": 24, "2012": 28, "mullingarshuffle": 128, "9gagtweets": 145, "fb": 27, "news": 65, "marinaalabau": 65, "tarifa": 65, "olympics?": 22, "proud": 24, "windsurf": 65, "g4s": 22, "fact": 24, "andwhat": 264, "ourgreatestteam": 65, "paralympics": 39, "olympics2012": 22, "rio2016": 58, "olympic..no": 25}}