{"timestamp": 1345829770500, "total": 6009, "urls": {"http://t.co/V5cJ08ni": 6, "http://t.co/fShQ23r2": 4, "http://t.co/sTkJ9LfZ": 14, "http://t.co/0OFezAPi": 4, "http://t.co/Y6ynM1B7": 8, "http://t.c": 4, "http://t.co/br8PkoQb": 3, "http://t.co/ypQpLoUp": 6, "http://t.co/4QEGvhEn": 5, "http://t.co/d8uxMK": 7, "http://t.co/syiNDT4e": 4, "http://t.co/J5Z3e272": 9, "http://t.co/S2qcoKI7": 18, "http://t.co/jADcDPkJ": 11, "http://t.co/8XzrtHFl": 5, "http://t.co/8CYXvwLh": 11, "http://t.co/wOvX7aUS": 4, "http://t.co/h": 50, "https://t.co/IQ4xr3EG": 4, "http://t.co/M8MOhAgm": 3, "http://t.co/f4": 4, "http://t.co/TZzDjM4U": 16, "http://t.co/DDgDWaLe": 9, "http://t.co/U2SATNJn": 4, "http://t.co/UnSipt7R": 5, "http://t.co/yy7Kv7p0": 4, "http://t.co/8capRTb5": 5, "http://t.co/0PHSaoDk": 15, "http://t.co/D6A6hMCl": 13, "http://t.co/SEV5fbZi": 9, "http://t.co/itm7Redc": 4, "http://t.co/hpjegm26": 6, "http://t.co/qnyZIEOE": 7, "http://t.co": 10, "http://t.co/NZcHOmrw": 7, "http://t.co/gGbnhXig": 8, "http://t.": 427, "http://t": 6, "http://t.co/CdQaW2QN": 4, "http://t.co/bxmrgQU5": 4}, "words": {"paralympic flame": 676, "opera house": 366, "paralympic athletics": 502, "paralympic": 1566, "torch": 462, "enter http://t": 492, "london2012 pic": 376, "the paralympic": 1178, "london": 472, "paralympic games": 326, "retweet": 418, "rt cadburyuk": 860, "cadburyuk": 434, "the beautiful": 368, "cadburyuk today's": 492, "paratorch http://t": 350, "at 20:12": 494, "to enter": 528, "iconic royal": 366, "inside london's": 370, "cadbury2012": 358, "today": 398, "the paralympics": 306, "boobs": 305, "tickets closes": 498, "beautiful glow": 370, "today's competition": 494, "house today": 366, "today paratorch": 360, "tickets": 361, "athletics tickets": 498, "royal opera": 368, "london's iconic": 366, "cadbury2012 tweet": 498, "any cadbury2012": 498, "glow inside": 370, "flame": 356, "http://t": 433, "flame adds": 368, "for paralympic": 554}, "tags": {"gamesmakers": 9, "teamusa": 10, "beckham": 19, "jamaica": 7, "win": 12, "paralympic": 133, "london2012,": 8, "olympics,": 18, "london2012.": 13, "badminton": 8, "london": 31, "cdwm": 7, "paratorch": 186, "flashbackfriday": 11, "teamgb": 109, "wonderwall": 24, "brazil": 7, "rememberthatkidinschool": 7, "usa": 7, "sportrightnow": 22, "tomdaleyphotoaday": 10, "4": 7, "cadbury2012": 358, "london2012_official_mobile_game": 23, "2012": 7, "olympian": 8, "wordsthatdescribeme": 8, "wheelchairtennis": 8, "etonmanor": 7, "twolves": 11, "giveaway": 8, "ff": 226, "news": 18, "paralympics2012": 9, "brazilnocorrupt": 7, "twibbon": 39, "socialolympics": 16, "feedbackfridays": 22, "paralympics": 65, "boisestate": 7}}