{"timestamp": 1346954800000, "total": 14015, "urls": {"http://t.co/hbDH5bPD": 43, "http://t.co/0yk2Mskn": 6, "http://t.co/": 13, "http://t.co/5k57Wn": 12, "http://t.c": 33, "http://t.co/pBrfa6EG": 13, "http://t.co/uStfzH0o": 4, "http://t.co/SJ9BQKqd": 38, "http://t.co/r4oe6iW8": 8, "http://t.co/N3BYkYkd": 10, "http://t.co/UOhajWzf": 5, "http://t.co/0Rjsy6qp": 10, "http://t.co/LONnElqB": 18, "http://t.co/0gUHy2pu": 24, "http://t.co/vHvKNF1U": 5, "http://t.co/Hh4eFtJn": 56, "http://t.co/xe6qtHoT": 17, "http://t.co/uwg6MKxk": 22, "http://t.co/4Vhgc9dc": 40, "http://t.co/LVJfk1sX": 43, "http://t.co/lJbJZfv8": 8, "http://t.co/boLgO5se": 7, "http://t.co/KKNbDu": 8, "http://t.co/kbxCJWYn": 11, "http://t.co/oezqL18m": 5, "http://t.co/lUZLQXiN": 11, "http://t.co/ZFqvvHZK": 5, "http://t.co/MWy3uaht": 10, "http://t.co/1Fgzig7J": 26, "http://t.co/7QxXzqCj": 5, "http://t.co/zFQSa9Dc": 18, "http://t.co/3tY9lk8M": 9, "http://t.co/v7c7yGCm": 4, "http://t.co/UYEWrSws": 6, "http://t.co": 53, "http://t.co/A6FZE5Hw": 6, "http://t.": 18, "http://t": 7, "http://t.co/8CYXvwLh": 14, "http://t.co/KFqlprOz": 6}, "words": {"gold": 1284, "paralympic": 1964, "olympic rower": 500, "tonight": 472, "the paralympic": 572, "london": 510, "teamgb": 870, "inspiring": 664, "and still": 512, "nervous": 504, "and inspiring": 1022, "amazing": 602, "won": 588, "stadium": 759, "2012": 453, "more": 459, "awesome": 670, "for real": 1006, "real": 544, "race": 476, "watching": 612, "hannah": 609, "still won": 466, "markhoppus": 499, "ducks pass": 498, "well done": 514, "rt markhoppus": 984, "medal": 482, "of ducks": 498, "stopped mid": 498, "the paralympics": 5076, "great": 464, "are awesome": 1012, "hannah cockroft": 586, "wheelchair rugby": 536, "rower stopped": 498, "olympic stadium": 1198, "paralympics": 6305, "a family": 498, "mid race": 498}, "tags": {"wcrugby": 44, "voteonedirection": 26, "goparalympicsgb": 124, "gold": 51, "wheresjoey": 26, "paralympic": 219, "competition": 31, "london": 37, "paralympicsgb": 76, "respect": 18, "c4paralympics": 81, "teamgb": 612, "olympicstadium": 24, "isitok": 18, "sportrightnow": 24, "amazing": 23, "paralympics.": 62, "goteamgb": 17, "vma's": 42, "homeadvantage\"": 29, "londonmarathon": 47, "bravery!": 45, "wheelchairrugby": 47, "fno": 18, "fb": 19, "channel4": 17, "teamsa": 24, "paralympics2012": 51, "goteamnl": 23, "roadcycling": 47, "thrillerthursday": 47, "superhumans": 20, "proud": 27, "su": 81, "inspirational": 23, "ourgreatestteam": 85, "paralympics": 2571, "athletics": 100, "getkidsgoing": 48, "murderball": 60}}