{"timestamp": 1345260949500, "total": 5322, "urls": {"http://t.co/z0LAj4al": 5, "http://t.co/luCmOnpe": 31, "http://t.co/KSIhs8Dz": 9, "http://t.co/AmrTw5Ng": 19, "http://t.co/zickbJ81": 4, "http://t.co/y2wikLCg": 119, "http://t.co/": 6, "http://t.co/lNQVlVgv": 3, "http://t.c": 7, "http://t.co/MB2Il1XE": 5, "http://t.co/yFBAQIKn": 3, "http://t.co/Y2rROZRh": 4, "http://t.co/RJxFrE0A": 4, "http://t.co/SDmn6qs5": 7, "http://t.co/NQzEksvR": 3, "http://t.co/0MZdZQQS": 6, "http://t.co/DCP9EO8l": 3, "http://t.co/EIa2o1SR": 5, "http://t.co/jQVvN4QM": 4, "http://t.co/Ryablc6m": 7, "http://t.co/NeoLHG4K": 3, "http://t.co/7fSJR3hB": 3, "http://t.co/wLam4FTo": 4, "http://t.co/ShoTnfGh": 6, "http://t.co/2439rpH7": 3, "http://t.co/y8bziKX5": 3, "http://t": 9, "http://t.co/N1mmMBy7": 3, "http://t.co/jTvX6q6m": 3, "http://t.co/e0DIAkIg": 3, "http://t.co/thi8Fqy5": 3, "http://t.co/9QHJ2asa": 7, "http://t.co/0P6DbT00": 3, "http://t.co/5uU7rLnU": 13, "http://t.co": 9, "https://t.co/aidcXj2z": 9, "http://t.co/W": 5, "http://t.co/4xgb5IMY": 6, "http://t.co/ZHixXNnf": 5, "http://t.co/UwO3XcH3": 13}, "words": {"gold": 281, "olympic tattoos": 266, "be held": 286, "they made": 246, "tour iii": 352, "normal tits": 274, "live world": 464, "tits": 549, "kst": 341, "17:30 pm": 262, "3rd": 250, "at jamsil": 634, "live": 255, "in seoul": 274, "smtown seoul": 354, "stadium": 471, "small tits": 274, "at 5:30": 278, "smtown": 430, "2012": 303, "seoul": 482, "big tits": 274, "rt tomdaley1994": 294, "sarahbarrow chrismears93": 254, "smtown live": 398, "5:30 pm": 292, "pm kst": 540, "today smtown": 308, "olympic games": 262, "world": 274, "world tour": 466, "olympic tits": 276, "jamsil": 427, "closing ceremony": 372, "at 17:30": 258, "today": 263, "stadium starts": 258, "olympic stadium": 922, "london": 353, "pm": 303}, "tags": {"jamaica": 6, "teamusa": 16, "win": 11, "india": 8, "sad": 6, "\u30aa\u30ea\u30f3\u30d4\u30c3\u30af": 9, "olympics.": 7, "london": 9, "oselevenquestions": 7, "jayparkconcert": 7, "merica": 7, "sportrightnow": 17, "teamgb": 13, "newbreedasia": 7, "smtownseoul": 10, "qrgames": 6, "usa": 13, "sports": 8, "london2012!": 6, "olympian": 8, "london2012_official_mobile_game": 31, "pats": 26, "proud": 6, "paralympians": 6, "serenawilliams": 8, "giveaway": 9, "ff": 7, "news": 15, "ioc": 7, "10": 7, "openingceremony": 6, "nfl": 8, "socialolympics": 17, "gators": 6, "tomdaley": 6, "smtown": 16, "paralympics": 7, "usainbolt": 8, "rio2016": 7, "swimming": 11}}