{"timestamp": 1346925999500, "total": 7496, "urls": {"http://t.co/VAg7Ullk": 18, "http://t.co/U1NVnM95": 4, "http://t.co/uSs": 6, "http://t.co/": 6, "http://t.c": 285, "http://t.co/8M7vChNR": 5, "http://t.co/aJY8MfZ": 12, "http://t.co/vfaSxHvz": 5, "http://t.co/f9fg7Wql": 5, "http://t.co/XZkMBIMX": 6, "http://t.co/sarfylOO": 7, "http://t.co/ZjgH8jbV": 5, "http://t.co/O9": 6, "http://t.co/YFW7lu8W": 35, "http://t.co/zuwusJmX": 7, "http://t.co/nglJQnRM": 8, "http://t.co/xe6qtHoT": 7, "http://t.co/IH910qeE": 5, "http://t.co/14wi6GES": 6, "http://t.co/IUpXz7Sy": 7, "http://t.co/ZpMmiyWY": 4, "http://t.co/p3YCnfHO": 7, "http://t.co/6vbGLtWJ": 5, "http://t.co/Toyuw2WF": 52, "http://t.co/xPh5zVDz": 9, "http://t.co/gQbGuHp1": 5, "http://t.co/OvVltxC": 6, "http://t.co/ymcnvdOr": 5, "http://t.co/TsgH3f35": 6, "http://t.co/nhoC6bkI": 4, "http://t.co/SZEdToBV": 4, "http://t.co/AzDoclEa": 17, "http://t.co": 16, "http://t.co/hGEG6JvT": 5, "http://t.": 7, "http://t": 28, "http://t.co/oNrmraSK": 12, "http://t.co/J8xDxUjA": 12, "http://t.co/BqatbWRe": 6, "http://t.co/3yU3krUP": 67}, "words": {"alex zinardi": 574, "hoping": 547, "gold": 798, "paralympic": 1377, "beatboxing": 542, "my hero's": 560, "london": 475, "hand cycling": 570, "just bumped": 568, "medallist one": 562, "closing": 620, "cycling gold": 568, "ceremony": 595, "and paralympic": 586, "hero's http://t.c": 552, "stephen": 545, "rascal": 538, "ex f1": 570, "zinardi ex": 564, "hawking": 543, "with dizzee": 1084, "gold medallist": 564, "dizzee rascal": 1076, "stephen hawking": 1084, "rt frankieboyle": 1070, "paralympics": 3021, "the closing": 1100, "i'm hoping": 1084, "i'm": 679, "the paralympics": 2722, "frankieboyle": 545, "paralympic hand": 570, "closing ceremony": 1152, "hawking beatboxing": 1084, "is stephen": 1084, "into alex": 570, "frankieboyle i'm": 1070, "f1 driver": 598, "dizzee": 542, "rt oscarpistorius": 582}, "tags": {"f1": 23, "teamusa": 11, "golf": 28, "goparalympicsgb": 19, "egypt": 13, "win": 31, "paralympic": 166, "teamnigeria": 31, "competition": 40, "london": 40, "paralympicsgb": 15, "sportrightnow": 25, "teamgb": 199, "wheelchairbasketball": 11, "inspiring": 10, "lastleg": 18, "paralympics?": 15, "retweet": 22, "london2012!": 74, "amazing": 12, "paralympics.": 33, "goteamgb": 11, "2012": 19, "football": 27, "bbcdp": 11, "2012paralympics": 10, "isitok": 26, "news": 25, "\u30d1\u30e9\u30ea\u30f3\u30d4\u30c3\u30af": 12, "thrillerthursday": 16, "sailing": 10, "socialolympics": 13, "blindfootball": 16, "5aside": 18, "inspirational": 12, "ourgreatestteam": 19, "paralympics": 966, "athletics": 34, "swimming": 11, "boccia": 24}}