{"timestamp": 1345005335500, "total": 8883, "urls": {"http://t.co/lwks5LjC)": 11, "http://t.co/vmHW5s5c": 9, "http://t.co/FheKCsRd": 26, "http://t.co/9FcxDAjb": 8, "http://t.co/id6tNlI4": 15, "http://t.co/dGRVpbea": 19, "http://t.co/i8FdXL72": 16, "http://t.co/gDY6rAOj": 15, "http://t.co/af": 8, "http://t.c": 13, "http://t.co/Om3eZME5": 22, "http://t.co/wx4zGjfe": 13, "http://t.co/m4loBPGw": 17, "http://t.co/CLFurZwN": 14, "http://t.co/SFjnItwi": 26, "http://t.co/6BXgzSBo": 30, "http://t.co/x2gi8vi1": 7, "http://t.co/JDee6TkS\u2026": 9, "http://t.co/7Te386Y4": 22, "http://t.co/og30Z113": 15, "http://t.co/QeSRTxdX": 7, "http://t.co/ShoTnfGh": 11, "http://t.co/TWPqLhj2": 8, "http://t.co/4Q0AwQlE": 10, "http://t.co/tbUIiG3V": 10, "http://t.co/ngfLQsaF": 16, "http://t.co/poY3KvSJ": 10, "http://t.co/obMeZHyW": 10, "http://t.co/UeEaSNGw": 22, "http://t.co/e0DIAkIg": 13, "http://t.co/": 15, "http://t.co/r7DFC9UT": 11, "http://t.co/qdlOqFnP": 13, "http://t.co": 18, "http://t.co/2UhJiwZr": 70, "http://t.co/aSXBhfaV": 7, "http://t.": 8, "http://t": 37, "http://t.co/hXoEydsA": 8, "http://t.co/32Y7Rtiw": 16}, "words": {"welcome home": 396, "gold": 485, "over": 590, "coleraine welcomes": 428, "back": 440, "one": 574, "olympians coleraine's": 428, "london": 810, "heroes welcome": 358, "its olympians": 428, "ceremony": 462, "to receive": 404, "a heroes": 392, "rowing medallists": 440, "can finally": 468, "2012": 729, "rt hilarious_dude": 412, "london 2012": 612, "welcome": 561, "the london": 484, "released back": 474, "olympic rowing": 442, "now": 549, "are over": 772, "i'm": 334, "hilarious_dude now": 402, "olympic games": 350, "his natur": 382, "olympic welcome": 406, "rt soinfinite": 324, "closing ceremony": 652, "soinfinite pic]120814-london": 328, "one direction": 596, "michael phelps": 520, "games": 323, "the ocean": 462, "be released": 474, "over michael": 472, "closing": 393, "rt louis_tomlinson": 388}, "tags": {"teamusa": 21, "gold": 15, "win": 36, "storybehindmyscar": 35, "\u30aa\u30ea\u30f3\u30d4\u30c3\u30af": 18, "london": 28, "gabbydouglas": 9, "sportrightnow": 18, "teamgb": 23, "20thingsidontlike": 10, "kiprotich": 16, "usa": 31, "socialmedia": 20, "liamtancockswimcap": 16, "sports": 10, "fatgirlproblems": 9, "mullingarshuffle": 19, "coolrunnings": 9, "teamfollowback": 12, "london2012_official_mobile_game": 12, "closingceremony": 24, "1dfact:": 27, "jamaicawegotabobsledteam": 42, "followmekobe": 17, "news": 27, "pleasestaycalm": 10, "\u9678\u4e0a": 13, "sharkweek": 14, "openingceremony": 12, "proud": 36, "fb": 11, "socialolympics": 16, "\u4f53\u64cd": 13, "withdrawal": 14, "paralympics": 13, "blackpeoplehobbies": 18, "olympics2012": 11, "usainbolt": 19, "uganda's": 10, "swimming": 13}}