{"timestamp": 1346227586000, "total": 13336, "urls": {"http://t.co/bRXUaA3T": 12, "http://t.co/8UjUZHrO": 9, "http://t.co/nNTwqsAF": 13, "http://t.co/70VeIuIr": 15, "http://t.co/EDOG4SuM": 41, "https://t.co/L9Eb1r2k": 16, "http://t.c": 17, "http://t.co/knJTtFxw": 10, "http://t.co/GIkLsrVS": 13, "http://t.co/whWZFvCM": 8, "http://t.co/LbfaCyKC": 83, "http://t.co/y3axoftZ": 46, "http://t.co/NH99yjpk": 9, "http://t.co/krg2rhcz": 26, "http://t.co/ixZK53B4": 10, "http://t.co/pYuJ9U8h": 10, "http://t.co/rWdv7": 34, "http://t.co/b3elrV9q": 26, "http://t.co/T5qJgwRS": 14, "http://t.co/usrLJd54": 14, "http://t.co/Ym6uviVK": 9, "http://t.co/UgelnxrY": 14, "http://t.co/K45ztahp": 22, "http://t.co/ZgFrhUO9": 10, "http://t.co/aFgUnzzm": 9, "http://t.co/XcHjvuyX": 21, "http://t.co/DSBuSpTe": 14, "http://t": 24, "http://t.co/IVlxEEe4": 15, "http://t.co/rMjNqD4V": 21, "http://t.co/G2LL4FnU\u201d": 13, "http://t.co/": 47, "http://t.co/pS1CJg5f": 15, "http://t.co/fdfKqRF": 9, "http://t.co": 16, "http://t.co/SDRfV7e6": 10, "http://t.co/0hlwnPvQ": 9, "http://t.": 67, "http://t.co/C0Lxh9dS": 19, "http://t.co/jjxs9oDQ": 11}, "words": {"paralympic games": 1340, "the 2012": 778, "let's go": 3630, "paralympic": 2851, "torch": 1026, "to go": 788, "tonight": 1092, "the paralympic": 2176, "london": 1179, "gb": 2019, "go": 2555, "good luck": 5496, "opening ceremony": 2730, "paralympics good": 3676, "ceremony": 1448, "the opening": 1098, "tomdaley1994 let's": 3580, "start": 656, "teamgb": 829, "today": 1299, "2012": 972, "team gb": 3902, "paralympics start": 610, "good": 3211, "opening": 1503, "paralympics opening": 614, "london 2012": 646, "rt tomdaley1994": 3708, "let's": 1863, "looking forward": 924, "2012 paralympics": 712, "go team": 3720, "the paralympics": 8170, "tomdaley1994": 1945, "games": 1103, "paralympic torch": 736, "team": 2420, "paralympics": 7136, "rt teamgb": 748, "luck": 2895}, "tags": {"paraly": 18, "ourgreate": 219, "goparalympicsgb": 71, "extraordinary2012": 128, "paralympic": 487, "11hourstogo": 62, "london": 46, "paratorch": 178, "teamwales": 22, "sportrightnow": 15, "teamgb": 283, "openingceremony.": 233, "paralympics?": 20, "goteamgb": 17, "disability": 15, "paralympics:": 55, "wca": 18, "proudparalympian": 32, "tomdaleyphotoaday": 74, "paralympics!": 45, "paralympics,": 30, "paralympics.": 56, "teamkenya": 28, "gop": 125, "london2012_official_mobile_game": 48, "atos": 68, "proudsa": 20, "torchrelay": 16, "news": 22, "paralympics2012": 36, "excited": 15, "goteamnl": 22, "teamireland": 73, "openingceremony": 160, "superhumans": 32, "socialolympics": 17, "windsor.": 19, "ourgreatestteam": 161, "paralympics": 1665, "paralympicgames": 17}}