{"timestamp": 1345916184500, "total": 3932, "urls": {"http://t.co/MrGOxVce": 2, "http://t.co/W7t7XYFv": 2, "http://t.co/lZXsusrP": 3, "http://t.co/9s1B6BdO": 4, "http://t.co/k9cqG2pM": 2, "http://t.co/Y6ynM1B7": 5, "http://t.co/4OEKBal9": 3, "http://t.c": 7, "http://t.co/W2K56Vda": 2, "http://t.co/ed1psIK7": 3, "http://t.co/GAMXRzsO": 6, "http://t.co/ypQpLoUp": 51, "http://t.co/syiNDT4e": 48, "http://t.co/a9myoxe5": 9, "http://t.co/MTq4u0Ca": 3, "http://t.co/HScQftIX": 3, "http://t.co/UnSipt7R": 3, "http://t.co/lUNEQdYs": 3, "http://t.co/U5mT7B5G": 2, "http://t.co/PXJq5Ymc": 3, "http://t.co/rEQofJmZ": 3, "http://t.co/Ej1HItfy": 4, "http://t.co/mD23Lz0s": 2, "http://t.co/fVx9bgeX": 10, "http://t.co/alZCeDrW": 3, "http://t.co/JSqKd8bD": 26, "http://t.co/w4VLfCzQ": 4, "http://t.co/Qh57Wk0x": 8, "http://t.co/KKUxWnUY": 3, "http://t.co/thi8Fqy5": 2, "http://t.co/XPA": 3, "http://t.co/EnlFo6QH": 2, "http://t.co/ECcS8PHW": 3, "http://t.co/6DOKB1xv": 3, "http://t.co": 3, "http://t.co/GIj6f4Am": 3, "http://t.": 10, "http://t": 3, "http://t.co/gITb8g18": 3, "http://t.co/SvCQmDJs": 2}, "words": {"paralympic flame": 142, "medalist": 143, "gold": 351, "paralympic athletics": 252, "win": 226, "paralympic": 512, "torch": 310, "final night": 250, "london": 214, "just retweet": 250, "olympic sport": 236, "message http": 244, "rt cadburyuk": 270, "out": 164, "ceremony": 135, "cadburyuk": 137, "this cadbury2012": 244, "bonus chance": 248, "of paralympic": 264, "sport": 142, "olympic gold": 286, "cadbury2012 message": 244, "today": 137, "2012": 184, "tickets": 151, "http": 151, "night": 162, "chance": 135, "the london": 158, "win tickets": 252, "medal": 156, "to win": 278, "gold medalist": 232, "the paralympic": 296, "the final": 254, "gold medal": 186, "up": 138, "games": 143, "team": 195, "a bonus": 248}, "tags": {"teamusa": 16, "paralympic": 51, "iwannaknowwhy": 76, "labordaysplash": 5, "olympics.": 5, "london": 12, "follow": 11, "sportrightnow": 18, "teamgb": 62, "r.i.p.aaliyah": 11, "cycling": 6, "hookem": 6, "photography)": 7, "datemeif": 6, "royal": 5, "olympian": 6, "eleicoes2012": 44, "interstellarx": 12, "bringsoftballback": 38, "cadbury2012": 130, "london2012_official_mobile_game": 20, "teamaaliyah": 10, "usa": 5, "rt#rt": 9, "paraflamecov": 7, "tfb": 13, "ifwt": 8, "14october": 5, "news": 18, "xfactor": 24, "brazilnocorrupt": 52, "libya": 5, "killenem": 8, "ut": 8, "goldmedalist": 6, "socialolympics": 16, "realheroes": 26, "fiel": 16, "ourgreatestteam": 5, "paralympics": 25}}