{"timestamp": 1345095335500, "total": 7007, "urls": {"http://t.co/dwTv67of": 7, "http://t.co/B9DxgAia": 11, "http://t.co/xXh": 7, "http://t.co/L": 12, "http://t.co/IdiW128Z": 6, "http://t.co/": 66, "http://t.c": 28, "http://t.co/UPK2QJWc": 6, "http://t.co/iPnT708H": 7, "http://t.co/2XtO2S7d": 10, "http://t.co/RSS30LIA": 5, "http://t.co/vDc3Lach": 24, "http://t.co/iLxEfpa4": 6, "http://t.co/sChOOnwG": 5, "http://t.co/DFAxseLz": 6, "http://t.co/cg7bJS1W": 6, "http://t.co/P7fh6pGp": 10, "http://t.co/XgK5dpm9": 12, "http://t.co/XTMddXN0": 5, "http://t.co/wMD23yl9": 6, "http://t.co/vt1OxbOY": 8, "http://t.co/RN2rMeRE": 20, "http://t.co/ejLxjIMv": 6, "http://t.co/zXhCnYFn": 5, "http://t.co/pkf0dWo6": 20, "http://t.co/JXzXyIeI": 7, "http://t.co/Swnqd532": 8, "http://t.co/PtoSYSgV": 6, "http://t.co/WiNSpXeB": 5, "http://t.co/clXXLcmm": 5, "http://t.co/rkICzteo": 6, "http://t.co/9AuYiNFq": 19, "http://t.co/VClCMtCT": 6, "http://t.co/8URrcSWc": 6, "http://t.co": 10, "http://t.co/rHG37PBp": 8, "http://t.": 19, "http://t": 7, "http://t.co/9lwSOvXz": 6, "http://t.co/0AoOvfFs": 5}, "words": {"wearing": 263, "gold": 1045, "perrie": 247, "over": 337, "perrie confirmed": 448, "about advertising": 326, "infographic": 635, "london": 619, "go": 735, "sponsors go": 1236, "just h": 356, "gold online": 1234, "confirmed": 247, "medal": 244, "h": 256, "olympic sponsors": 1228, "olympic gold": 284, "online": 651, "that zayn": 456, "yoududezayn perrie": 346, "2012": 500, "an interview": 458, "ceremony": 479, "london 2012": 414, "sponsors": 624, "olympics sponsorships": 310, "online infographic": 1226, "for gold": 1246, "the closing": 510, "zayn": 298, "rt yoududezayn": 346, "are over": 304, "olympic games": 244, "not wearing": 408, "hat": 278, "closing ceremony": 760, "team": 333, "her hat": 456, "closing": 464, "more": 310}, "tags": {"olympics?": 15, "teamusa": 25, "win": 23, "paralympic": 14, "zaynfact": 17, "assange": 15, "olympics,": 10, "olympics.": 16, "london": 49, "nba": 10, "education": 25, "sportrightnow": 18, "teamgb": 24, "somalia?": 12, "confirmed": 17, "usa": 17, "\u0e2b": 11, "socialmedia": 50, "gazan": 11, "tweeps": 9, "closingceremony": 9, "marketing": 9, "london2012_official_mobile_game": 42, "1stave": 9, "india": 25, "watch": 44, "usmnt": 10, "news": 36, "nfl": 9, "14": 13, "science": 25, "teamfollowback": 14, "youtube": 46, "socialolympics": 15, "mashable": 12, "tech": 13, "social": 10, "paralympics": 22, "didyouknow": 19, "swimming": 12}}