{"timestamp": 1343504246000, "total": 151891, "urls": {"http://t.co/2CUFdLGR": 30, "http://t.co/2L008A3c": 90, "http://t.co/zTQq536F": 66, "http://t.co/": 191, "http://t.co/Vykhy36d": 30, "http://t.c": 112, "http://t.co/4PaZKtNx": 65, "http://t.co/OaT0vASX": 38, "http://t.co/ymQVHyR6": 226, "http://t.co/1r9lxjQm": 101, "http://t.co/Rs3e8uB0": 33, "http://t.co/C5Wdzcnb": 67, "http://t.co/ER3mkv7A": 37, "http://t.co/rT0fRt5C": 67, "http://t.co/09uqJJrL": 33, "http://t.co/WXZKgwXT": 58, "http://t.co/DHxg8Jom": 56, "http://t.co/ki2uEgGq": 36, "http://t.co/vJJBtBTY": 48, "http://t.co/udYBU8Ir": 92, "http://t.co/rIehfaRe": 48, "http://t.": 247, "http://t.co/0sJfypJi": 33, "http://t.co/91EDfiPx": 70, "http://t.co/u9AXQVyO": 42, "http://t.co/veD1f02H": 37, "http://t.co/4oxpYciP": 599, "http://t.co/i3": 60, "http://t.co/9LyaclIM": 35, "http://t.co/OCRmFWdc": 63, "http://t.co/gYDMVKkq": 191, "http://t.co/pBGwMD2N": 54, "http://t.co/8O7i2MsT": 33, "http://t.co/eHhwAKG9": 341, "http://t.co/nJFhbdJ6": 32, "http://t.co": 394, "http://t.co/WeQs2gMb": 64, "http://t": 149, "http://t.co/1lJAWOkB": 83, "http://t.co/LK9bRFbc": 29}, "words": {"love": 4337, "gold": 6344, "getgluehd nbcolympics": 4230, "one": 5295, "go": 4293, "badminton": 4101, "london": 6965, "opening ceremony": 8944, "the 2012": 3878, "olympic sport": 4844, "sport": 4799, "out": 4356, "ceremony": 5814, "usa": 8092, "it's": 3778, "opening": 5792, "day": 4550, "i'm watching": 4690, "2012": 6609, "to watch": 5850, "watching": 16759, "london 2012": 3770, "time": 3854, "watch": 7783, "women's": 5785, "i love": 4216, "now": 4096, "i'm": 7199, "olympic games": 5222, "ryan lochte": 4660, "olympic volleyball": 9012, "volleyball": 16032, "games": 4249, "team": 6739, "gymnastics": 4166, "olympic opening": 4764, "swimming": 3884, "athletes": 3763, "think": 3607, "first": 4209}, "tags": {"teamusa": 2129, "nw": 145, "getgluehd!": 1181, "handball": 199, "jjoo": 175, "olympics.": 686, "gymnastics": 425, "olympic2012": 172, "nbc": 248, "teamgb": 840, "olympics\u201d": 255, "openi": 294, "teamusa!": 203, "usa": 2346, "fencing": 464, "boxing": 282, "olympics,": 151, "amazing": 144, "merica": 163, "bbc2012": 189, "2012londonolympics": 1043, "olympicceremony": 168, "2012": 169, "nbcfail": 336, "fb": 217, "beachvolleyball": 183, "news": 141, "realtweet": 204, "silver": 236, "gousa": 239, "london2012.": 158, "openingceremony": 1067, "usavolleyball": 265, "womensvolleyball": 170, "volleyball": 1383, "badminton": 285, "london": 378, "olympics2012": 567, "getgluehd": 1988, "swimming": 741}}